CHANGES.txt
README.txt
buildout.cfg
setup.py
bootstrap/bootstrap.py
src/zc/__init__.py
src/zc.z3monitor.egg-info/PKG-INFO
src/zc.z3monitor.egg-info/SOURCES.txt
src/zc.z3monitor.egg-info/dependency_links.txt
src/zc.z3monitor.egg-info/namespace_packages.txt
src/zc.z3monitor.egg-info/not-zip-safe
src/zc.z3monitor.egg-info/requires.txt
src/zc.z3monitor.egg-info/top_level.txt
src/zc/z3monitor/CHANGES.txt
src/zc/z3monitor/README.txt
src/zc/z3monitor/__init__.py
src/zc/z3monitor/configure.zcml
src/zc/z3monitor/initialize.test
src/zc/z3monitor/interfaces.py
src/zc/z3monitor/sleeptest.zcml
src/zc/z3monitor/tests.py