Metadata-Version: 1.0
Name: zc.z3monitor
Version: 0.8.0
Summary: A network-accessible command-line interface to monitor a Zope 3 process.
